{"trial_id": "108d265670a47344554b6cc976612421", "hyperparameters": {"space": [{"class_name": "Int", "config": {"name": "units", "default": null, "conditions": [], "min_value": 32, "max_value": 1024, "step": 32, "sampling": null}}, {"class_name": "Int", "config": {"name": "units_2", "default": null, "conditions": [], "min_value": 8, "max_value": 128, "step": 16, "sampling": null}}, {"class_name": "Choice", "config": {"name": "learning_rate", "default": 0.01, "conditions": [], "values": [0.01, 0.001, 0.0001], "ordered": true}}], "values": {"units": 992, "units_2": 88, "learning_rate": 0.001, "tuner/epochs": 10, "tuner/initial_epoch": 0, "tuner/bracket": 0, "tuner/round": 0}}, "metrics": {"metrics": {"loss": {"direction": "min", "observations": [{"value": [0.5716837048530579], "step": 0}]}, "accuracy": {"direction": "max", "observations": [{"value": [0.7340978384017944], "step": 0}]}, "val_loss": {"direction": "min", "observations": [{"value": [0.5509620904922485], "step": 0}]}, "val_accuracy": {"direction": "max", "observations": [{"value": [0.7389698624610901], "step": 0}]}}}, "score": 0.7389698624610901, "best_step": 0, "status": "COMPLETED"}